ChangeLog
INSTALL
MANIFEST.in
Makefile
README
python-config.spec
python_config.py
setup.py
python_config.egg-info/PKG-INFO
python_config.egg-info/SOURCES.txt
python_config.egg-info/dependency_links.txt
python_config.egg-info/top_level.txt
tests/test.conf
tests/test_file_reading.py
tests/test_parsing.py